{"year":2020,"scope":"state_house","contest_type":"president","meta":{"match_coverage_pct":82.9,"matched_precinct_keys":2419,"total_precinct_keys":2918,"source":"batch_shatter_vap_party_split","office":"US PRESIDENT"},"general":{"results":{"1":{"dem_votes":18185,"rep_votes":30468,"other_votes":638,"total_votes":49291,"dem_candidate":"Joseph R. Biden","rep_candidate":"Donald J. Trump","margin":12283,"margin_pct":24.92,"winner":"REP","competitiveness":{"color":"#cb181d"}},"2":{"dem_votes":30928,"rep_votes":18987,"other_votes":674,"total_votes":50589,"dem_candidate":"Joseph R. Biden","rep_candidate":"Donald J. Trump","margin":-11941,"margin_pct":-23.6,"winner":"DEM","competitiveness":{"color":"#3182bd"}},"3":{"dem_votes":18582,"rep_votes":27365,"other_votes":735,"total_votes":46682,"dem_candidate":"Joseph R. Biden","rep_candidate":"Donald J. Trump","margin":8783,"margin_pct":18.81,"winner":"REP","competitiveness":{"color":"#ef3b2c"}},"4":{"dem_votes":15699,"rep_votes":22951,"other_votes":328,"total_votes":38978,"dem_candidate":"Joseph R. Biden","rep_candidate":"Donald J. Trump","margin":7252,"margin_pct":18.61,"winner":"REP","competitiveness":{"color":"#ef3b2c"}},"5":{"dem_votes":21012,"rep_votes":20928,"other_votes":515,"total_votes":42455,"dem_candidate":"Joseph R. Biden","rep_candidate":"Donald J. Trump","margin":-84,"margin_pct":-0.2,"winner":"DEM","competitiveness":{"color":"#f7f7f7"}},"6":{"dem_votes":12933,"rep_votes":20083,"other_votes":584,"total_votes":33600,"dem_candidate":"Joseph R. Biden","rep_candidate":"Donald J. Trump","margin":7150,"margin_pct":21.28,"winner":"REP","competitiveness":{"color":"#cb181d"}},"7":{"dem_votes":19978,"rep_votes":27258,"other_votes":716,"total_votes":47952,"dem_candidate":"Joseph R. Biden","rep_candidate":"Donald J. Trump","margin":7280,"margin_pct":15.18,"winner":"REP","competitiveness":{"color":"#ef3b2c"}},"8":{"dem_votes":24337,"rep_votes":19977,"other_votes":669,"total_votes":44983,"dem_candidate":"Joseph R. Biden","rep_candidate":"Donald J. Trump","margin":-4360,"margin_pct":-9.69,"winner":"DEM","competitiveness":{"color":"#9ecae1"}},"9":{"dem_votes":22915,"rep_votes":19005,"other_votes":670,"total_votes":42590,"dem_candidate":"Joseph R. Biden","rep_candidate":"Donald J. Trump","margin":-3910,"margin_pct":-9.18,"winner":"DEM","competitiveness":{"color":"#9ecae1"}},"10":{"dem_votes":17283,"rep_votes":21551,"other_votes":440,"total_votes":39274,"dem_candidate":"Joseph R. Biden","rep_candidate":"Donald J. Trump","margin":4268,"margin_pct":10.87,"winner":"REP","competitiveness":{"color":"#ef3b2c"}},"11":{"dem_votes":30224,"rep_votes":16989,"other_votes":975,"total_votes":48188,"dem_candidate":"Joseph R. Biden","rep_candidate":"Donald J. Trump","margin":-13235,"margin_pct":-27.47,"winner":"DEM","competitiveness":{"color":"#3182bd"}},"12":{"dem_votes":19634,"rep_votes":22744,"other_votes":309,"total_votes":42687,"dem_candidate":"Joseph R. Biden","rep_candidate":"Donald J. Trump","margin":3110,"margin_pct":7.29,"winner":"REP","competitiveness":{"color":"#fb6a4a"}},"13":{"dem_votes":14659,"rep_votes":33695,"other_votes":724,"total_votes":49078,"dem_candidate":"Joseph R. Biden","rep_candidate":"Donald J. Trump","margin":19036,"margin_pct":38.79,"winner":"REP","competitiveness":{"color":"#a50f15"}},"14":{"dem_votes":8663,"rep_votes":14797,"other_votes":702,"total_votes":24162,"dem_candidate":"Joseph R. Biden","rep_candidate":"Donald J. Trump","margin":6134,"margin_pct":25.39,"winner":"REP","competitiveness":{"color":"#cb181d"}},"15":{"dem_votes":12715,"rep_votes":22763,"other_votes":908,"total_votes":36386,"dem_candidate":"Joseph R. Biden","rep_candidate":"Donald J. Trump","margin":10048,"margin_pct":27.62,"winner":"REP","competitiveness":{"color":"#cb181d"}},"16":{"dem_votes":14611,"rep_votes":30474,"other_votes":771,"total_votes":45856,"dem_candidate":"Joseph R. Biden","rep_candidate":"Donald J. Trump","margin":15863,"margin_pct":34.59,"winner":"REP","competitiveness":{"color":"#a50f15"}},"17":{"dem_votes":21493,"rep_votes":36037,"other_votes":655,"total_votes":58185,"dem_candidate":"Joseph R. Biden","rep_candidate":"Donald J. Trump","margin":14544,"margin_pct":25.0,"winner":"REP","competitiveness":{"color":"#cb181d"}},"18":{"dem_votes":25195,"rep_votes":22142,"other_votes":900,"total_votes":48237,"dem_candidate":"Joseph R. Biden","rep_candidate":"Donald J. Trump","margin":-3053,"margin_pct":-6.33,"winner":"DEM","competitiveness":{"color":"#9ecae1"}},"19":{"dem_votes":30409,"rep_votes":39313,"other_votes":1023,"total_votes":70745,"dem_candidate":"Joseph R. Biden","rep_candidate":"Donald J. Trump","margin":8904,"margin_pct":12.59,"winner":"REP","competitiveness":{"color":"#ef3b2c"}},"20":{"dem_votes":22351,"rep_votes":21688,"other_votes":798,"total_votes":44837,"dem_candidate":"Joseph R. Biden","rep_candidate":"Donald J. Trump","margin":-663,"margin_pct":-1.48,"winner":"DEM","competitiveness":{"color":"#c6dbef"}},"21":{"dem_votes":29058,"rep_votes":15791,"other_votes":811,"total_votes":45660,"dem_candidate":"Joseph R. Biden","rep_candidate":"Donald J. Trump","margin":-13267,"margin_pct":-29.06,"winner":"DEM","competitiveness":{"color":"#3182bd"}},"22":{"dem_votes":18292,"rep_votes":27087,"other_votes":364,"total_votes":45743,"dem_candidate":"Joseph R. Biden","rep_candidate":"Donald J. Trump","margin":8795,"margin_pct":19.23,"winner":"REP","competitiveness":{"color":"#ef3b2c"}},"23":{"dem_votes":27939,"rep_votes":19555,"other_votes":338,"total_votes":47832,"dem_candidate":"Joseph R. Biden","rep_candidate":"Donald J. Trump","margin":-8384,"margin_pct":-17.53,"winner":"DEM","competitiveness":{"color":"#6baed6"}},"24":{"dem_votes":21972,"rep_votes":20790,"other_votes":425,"total_votes":43187,"dem_candidate":"Joseph R. Biden","rep_candidate":"Donald J. Trump","margin":-1182,"margin_pct":-2.74,"winner":"DEM","competitiveness":{"color":"#c6dbef"}},"25":{"dem_votes":24729,"rep_votes":24618,"other_votes":472,"total_votes":49819,"dem_candidate":"Joseph R. Biden","rep_candidate":"Donald J. Trump","margin":-111,"margin_pct":-0.22,"winner":"DEM","competitiveness":{"color":"#f7f7f7"}},"26":{"dem_votes":17131,"rep_votes":27378,"other_votes":721,"total_votes":45230,"dem_candidate":"Joseph R. Biden","rep_candidate":"Donald J. Trump","margin":10247,"margin_pct":22.66,"winner":"REP","competitiveness":{"color":"#cb181d"}},"27":{"dem_votes":28014,"rep_votes":17821,"other_votes":327,"total_votes":46162,"dem_candidate":"Joseph R. Biden","rep_candidate":"Donald J. Trump","margin":-10193,"margin_pct":-22.08,"winner":"DEM","competitiveness":{"color":"#3182bd"}},"28":{"dem_votes":16748,"rep_votes":28809,"other_votes":707,"total_votes":46264,"dem_candidate":"Joseph R. Biden","rep_candidate":"Donald J. Trump","margin":12061,"margin_pct":26.07,"winner":"REP","competitiveness":{"color":"#cb181d"}},"29":{"dem_votes":2052,"rep_votes":778,"other_votes":118,"total_votes":2948,"dem_candidate":"Joseph R. Biden","rep_candidate":"Donald J. Trump","margin":-1274,"margin_pct":-43.22,"winner":"DEM","competitiveness":{"color":"#08306b"}},"30":{"dem_votes":60102,"rep_votes":12995,"other_votes":1120,"total_votes":74217,"dem_candidate":"Joseph R. Biden","rep_candidate":"Donald J. Trump","margin":-47107,"margin_pct":-63.47,"winner":"DEM","competitiveness":{"color":"#08306b"}},"31":{"dem_votes":60072,"rep_votes":12885,"other_votes":1101,"total_votes":74058,"dem_candidate":"Joseph R. Biden","rep_candidate":"Donald J. Trump","margin":-47187,"margin_pct":-63.72,"winner":"DEM","competitiveness":{"color":"#08306b"}},"32":{"dem_votes":22897,"rep_votes":18681,"other_votes":418,"total_votes":41996,"dem_candidate":"Joseph R. Biden","rep_candidate":"Donald J. Trump","margin":-4216,"margin_pct":-10.04,"winner":"DEM","competitiveness":{"color":"#6baed6"}},"33":{"dem_votes":30324,"rep_votes":17531,"other_votes":920,"total_votes":48775,"dem_candidate":"Joseph R. Biden","rep_candidate":"Donald J. Trump","margin":-12793,"margin_pct":-26.23,"winner":"DEM","competitiveness":{"color":"#3182bd"}},"34":{"dem_votes":31226,"rep_votes":18635,"other_votes":1004,"total_votes":50865,"dem_candidate":"Joseph R. Biden","rep_candidate":"Donald J. Trump","margin":-12591,"margin_pct":-24.75,"winner":"DEM","competitiveness":{"color":"#3182bd"}},"35":{"dem_votes":29663,"rep_votes":18160,"other_votes":972,"total_votes":48795,"dem_candidate":"Joseph R. Biden","rep_candidate":"Donald J. Trump","margin":-11503,"margin_pct":-23.57,"winner":"DEM","competitiveness":{"color":"#3182bd"}},"36":{"dem_votes":29864,"rep_votes":17724,"other_votes":949,"total_votes":48537,"dem_candidate":"Joseph R. Biden","rep_candidate":"Donald J. Trump","margin":-12140,"margin_pct":-25.01,"winner":"DEM","competitiveness":{"color":"#3182bd"}},"37":{"dem_votes":29459,"rep_votes":18117,"other_votes":979,"total_votes":48555,"dem_candidate":"Joseph R. Biden","rep_candidate":"Donald J. Trump","margin":-11342,"margin_pct":-23.36,"winner":"DEM","competitiveness":{"color":"#3182bd"}},"38":{"dem_votes":31873,"rep_votes":15448,"other_votes":898,"total_votes":48219,"dem_candidate":"Joseph R. Biden","rep_candidate":"Donald J. Trump","margin":-16425,"margin_pct":-34.06,"winner":"DEM","competitiveness":{"color":"#08519c"}},"39":{"dem_votes":29953,"rep_votes":17222,"other_votes":900,"total_votes":48075,"dem_candidate":"Joseph R. Biden","rep_candidate":"Donald J. Trump","margin":-12731,"margin_pct":-26.48,"winner":"DEM","competitiveness":{"color":"#3182bd"}},"40":{"dem_votes":30265,"rep_votes":19380,"other_votes":1006,"total_votes":50651,"dem_candidate":"Joseph R. Biden","rep_candidate":"Donald J. Trump","margin":-10885,"margin_pct":-21.49,"winner":"DEM","competitiveness":{"color":"#3182bd"}},"41":{"dem_votes":30458,"rep_votes":17807,"other_votes":987,"total_votes":49252,"dem_candidate":"Joseph R. Biden","rep_candidate":"Donald J. Trump","margin":-12651,"margin_pct":-25.69,"winner":"DEM","competitiveness":{"color":"#3182bd"}},"42":{"dem_votes":19260,"rep_votes":8000,"other_votes":603,"total_votes":27863,"dem_candidate":"Joseph R. Biden","rep_candidate":"Donald J. Trump","margin":-11260,"margin_pct":-40.41,"winner":"DEM","competitiveness":{"color":"#08306b"}},"43":{"dem_votes":18196,"rep_votes":19284,"other_votes":568,"total_votes":38048,"dem_candidate":"Joseph R. Biden","rep_candidate":"Donald J. Trump","margin":1088,"margin_pct":2.86,"winner":"REP","competitiveness":{"color":"#fcae91"}},"44":{"dem_votes":24806,"rep_votes":15704,"other_votes":779,"total_votes":41289,"dem_candidate":"Joseph R. Biden","rep_candidate":"Donald J. Trump","margin":-9102,"margin_pct":-22.04,"winner":"DEM","competitiveness":{"color":"#3182bd"}},"45":{"dem_votes":22208,"rep_votes":17043,"other_votes":699,"total_votes":39950,"dem_candidate":"Joseph R. Biden","rep_candidate":"Donald J. Trump","margin":-5165,"margin_pct":-12.93,"winner":"DEM","competitiveness":{"color":"#6baed6"}},"46":{"dem_votes":14089,"rep_votes":25878,"other_votes":276,"total_votes":40243,"dem_candidate":"Joseph R. Biden","rep_candidate":"Donald J. Trump","margin":11789,"margin_pct":29.29,"winner":"REP","competitiveness":{"color":"#cb181d"}},"47":{"dem_votes":14377,"rep_votes":18760,"other_votes":254,"total_votes":33391,"dem_candidate":"Joseph R. Biden","rep_candidate":"Donald J. Trump","margin":4383,"margin_pct":13.13,"winner":"REP","competitiveness":{"color":"#ef3b2c"}},"48":{"dem_votes":18990,"rep_votes":16926,"other_votes":498,"total_votes":36414,"dem_candidate":"Joseph R. Biden","rep_candidate":"Donald J. Trump","margin":-2064,"margin_pct":-5.67,"winner":"DEM","competitiveness":{"color":"#9ecae1"}},"49":{"dem_votes":30568,"rep_votes":17028,"other_votes":993,"total_votes":48589,"dem_candidate":"Joseph R. Biden","rep_candidate":"Donald J. Trump","margin":-13540,"margin_pct":-27.87,"winner":"DEM","competitiveness":{"color":"#3182bd"}},"50":{"dem_votes":31155,"rep_votes":16920,"other_votes":636,"total_votes":48711,"dem_candidate":"Joseph R. Biden","rep_candidate":"Donald J. Trump","margin":-14235,"margin_pct":-29.22,"winner":"DEM","competitiveness":{"color":"#3182bd"}},"51":{"dem_votes":15988,"rep_votes":23260,"other_votes":547,"total_votes":39795,"dem_candidate":"Joseph R. Biden","rep_candidate":"Donald J. Trump","margin":7272,"margin_pct":18.27,"winner":"REP","competitiveness":{"color":"#ef3b2c"}},"52":{"dem_votes":17507,"rep_votes":26546,"other_votes":527,"total_votes":44580,"dem_candidate":"Joseph R. Biden","rep_candidate":"Donald J. Trump","margin":9039,"margin_pct":20.28,"winner":"REP","competitiveness":{"color":"#cb181d"}},"53":{"dem_votes":16538,"rep_votes":27260,"other_votes":758,"total_votes":44556,"dem_candidate":"Joseph R. Biden","rep_candidate":"Donald J. Trump","margin":10722,"margin_pct":24.06,"winner":"REP","competitiveness":{"color":"#cb181d"}},"54":{"dem_votes":16775,"rep_votes":15373,"other_votes":361,"total_votes":32509,"dem_candidate":"Joseph R. Biden","rep_candidate":"Donald J. Trump","margin":-1402,"margin_pct":-4.31,"winner":"DEM","competitiveness":{"color":"#c6dbef"}},"55":{"dem_votes":18229,"rep_votes":27226,"other_votes":560,"total_votes":46015,"dem_candidate":"Joseph R. Biden","rep_candidate":"Donald J. Trump","margin":8997,"margin_pct":19.55,"winner":"REP","competitiveness":{"color":"#ef3b2c"}},"56":{"dem_votes":37299,"rep_votes":10345,"other_votes":693,"total_votes":48337,"dem_candidate":"Joseph R. Biden","rep_candidate":"Donald J. Trump","margin":-26954,"margin_pct":-55.76,"winner":"DEM","competitiveness":{"color":"#08306b"}},"57":{"dem_votes":28604,"rep_votes":18501,"other_votes":704,"total_votes":47809,"dem_candidate":"Joseph R. Biden","rep_candidate":"Donald J. Trump","margin":-10103,"margin_pct":-21.13,"winner":"DEM","competitiveness":{"color":"#3182bd"}},"58":{"dem_votes":29448,"rep_votes":16800,"other_votes":654,"total_votes":46902,"dem_candidate":"Joseph R. Biden","rep_candidate":"Donald J. Trump","margin":-12648,"margin_pct":-26.97,"winner":"DEM","competitiveness":{"color":"#3182bd"}},"59":{"dem_votes":27983,"rep_votes":19484,"other_votes":686,"total_votes":48153,"dem_candidate":"Joseph R. Biden","rep_candidate":"Donald J. Trump","margin":-8499,"margin_pct":-17.65,"winner":"DEM","competitiveness":{"color":"#6baed6"}},"60":{"dem_votes":28868,"rep_votes":17158,"other_votes":660,"total_votes":46686,"dem_candidate":"Joseph R. Biden","rep_candidate":"Donald J. Trump","margin":-11710,"margin_pct":-25.08,"winner":"DEM","competitiveness":{"color":"#3182bd"}},"61":{"dem_votes":29982,"rep_votes":16291,"other_votes":694,"total_votes":46967,"dem_candidate":"Joseph R. Biden","rep_candidate":"Donald J. Trump","margin":-13691,"margin_pct":-29.15,"winner":"DEM","competitiveness":{"color":"#3182bd"}},"62":{"dem_votes":28200,"rep_votes":19060,"other_votes":708,"total_votes":47968,"dem_candidate":"Joseph R. Biden","rep_candidate":"Donald J. Trump","margin":-9140,"margin_pct":-19.05,"winner":"DEM","competitiveness":{"color":"#6baed6"}},"63":{"dem_votes":21740,"rep_votes":20315,"other_votes":636,"total_votes":42691,"dem_candidate":"Joseph R. Biden","rep_candidate":"Donald J. Trump","margin":-1425,"margin_pct":-3.34,"winner":"DEM","competitiveness":{"color":"#c6dbef"}},"64":{"dem_votes":17085,"rep_votes":25741,"other_votes":574,"total_votes":43400,"dem_candidate":"Joseph R. Biden","rep_candidate":"Donald J. Trump","margin":8656,"margin_pct":19.94,"winner":"REP","competitiveness":{"color":"#ef3b2c"}},"65":{"dem_votes":15992,"rep_votes":31301,"other_votes":516,"total_votes":47809,"dem_candidate":"Joseph R. Biden","rep_candidate":"Donald J. Trump","margin":15309,"margin_pct":32.02,"winner":"REP","competitiveness":{"color":"#a50f15"}},"66":{"dem_votes":41447,"rep_votes":24854,"other_votes":1203,"total_votes":67504,"dem_candidate":"Joseph R. Biden","rep_candidate":"Donald J. Trump","margin":-16593,"margin_pct":-24.58,"winner":"DEM","competitiveness":{"color":"#3182bd"}},"67":{"dem_votes":12456,"rep_votes":33869,"other_votes":463,"total_votes":46788,"dem_candidate":"Joseph R. Biden","rep_candidate":"Donald J. Trump","margin":21413,"margin_pct":45.77,"winner":"REP","competitiveness":{"color":"#67000d"}},"68":{"dem_votes":18150,"rep_votes":26106,"other_votes":687,"total_votes":44943,"dem_candidate":"Joseph R. Biden","rep_candidate":"Donald J. Trump","margin":7956,"margin_pct":17.7,"winner":"REP","competitiveness":{"color":"#ef3b2c"}},"69":{"dem_votes":18135,"rep_votes":32371,"other_votes":741,"total_votes":51247,"dem_candidate":"Joseph R. Biden","rep_candidate":"Donald J. Trump","margin":14236,"margin_pct":27.78,"winner":"REP","competitiveness":{"color":"#cb181d"}},"70":{"dem_votes":10146,"rep_votes":33424,"other_votes":494,"total_votes":44064,"dem_candidate":"Joseph R. Biden","rep_candidate":"Donald J. Trump","margin":23278,"margin_pct":52.83,"winner":"REP","competitiveness":{"color":"#67000d"}},"71":{"dem_votes":27949,"rep_votes":11680,"other_votes":656,"total_votes":40285,"dem_candidate":"Joseph R. Biden","rep_candidate":"Donald J. Trump","margin":-16269,"margin_pct":-40.38,"winner":"DEM","competitiveness":{"color":"#08306b"}},"72":{"dem_votes":31099,"rep_votes":11264,"other_votes":705,"total_votes":43068,"dem_candidate":"Joseph R. Biden","rep_candidate":"Donald J. Trump","margin":-19835,"margin_pct":-46.06,"winner":"DEM","competitiveness":{"color":"#08306b"}},"73":{"dem_votes":17867,"rep_votes":20738,"other_votes":647,"total_votes":39252,"dem_candidate":"Joseph R. Biden","rep_candidate":"Donald J. Trump","margin":2871,"margin_pct":7.31,"winner":"REP","competitiveness":{"color":"#fb6a4a"}},"74":{"dem_votes":24910,"rep_votes":23974,"other_votes":839,"total_votes":49723,"dem_candidate":"Joseph R. Biden","rep_candidate":"Donald J. Trump","margin":-936,"margin_pct":-1.88,"winner":"DEM","competitiveness":{"color":"#c6dbef"}},"75":{"dem_votes":16943,"rep_votes":22055,"other_votes":581,"total_votes":39579,"dem_candidate":"Joseph R. Biden","rep_candidate":"Donald J. Trump","margin":5112,"margin_pct":12.92,"winner":"REP","competitiveness":{"color":"#ef3b2c"}},"76":{"dem_votes":16535,"rep_votes":26945,"other_votes":593,"total_votes":44073,"dem_candidate":"Joseph R. Biden","rep_candidate":"Donald J. Trump","margin":10410,"margin_pct":23.62,"winner":"REP","competitiveness":{"color":"#cb181d"}},"77":{"dem_votes":11972,"rep_votes":38628,"other_votes":673,"total_votes":51273,"dem_candidate":"Joseph R. Biden","rep_candidate":"Donald J. Trump","margin":26656,"margin_pct":51.99,"winner":"REP","competitiveness":{"color":"#67000d"}},"78":{"dem_votes":12614,"rep_votes":36056,"other_votes":570,"total_votes":49240,"dem_candidate":"Joseph R. Biden","rep_candidate":"Donald J. Trump","margin":23442,"margin_pct":47.61,"winner":"REP","competitiveness":{"color":"#67000d"}},"79":{"dem_votes":19231,"rep_votes":31030,"other_votes":555,"total_votes":50816,"dem_candidate":"Joseph R. Biden","rep_candidate":"Donald J. Trump","margin":11799,"margin_pct":23.22,"winner":"REP","competitiveness":{"color":"#cb181d"}},"80":{"dem_votes":10872,"rep_votes":32876,"other_votes":605,"total_votes":44353,"dem_candidate":"Joseph R. Biden","rep_candidate":"Donald J. Trump","margin":22004,"margin_pct":49.61,"winner":"REP","competitiveness":{"color":"#67000d"}},"81":{"dem_votes":11764,"rep_votes":31782,"other_votes":615,"total_votes":44161,"dem_candidate":"Joseph R. Biden","rep_candidate":"Donald J. Trump","margin":20018,"margin_pct":45.33,"winner":"REP","competitiveness":{"color":"#67000d"}},"82":{"dem_votes":17888,"rep_votes":21198,"other_votes":631,"total_votes":39717,"dem_candidate":"Joseph R. Biden","rep_candidate":"Donald J. Trump","margin":3310,"margin_pct":8.33,"winner":"REP","competitiveness":{"color":"#fb6a4a"}},"83":{"dem_votes":21491,"rep_votes":39186,"other_votes":877,"total_votes":61554,"dem_candidate":"Joseph R. Biden","rep_candidate":"Donald J. Trump","margin":17695,"margin_pct":28.75,"winner":"REP","competitiveness":{"color":"#cb181d"}},"84":{"dem_votes":18191,"rep_votes":36948,"other_votes":740,"total_votes":55879,"dem_candidate":"Joseph R. Biden","rep_candidate":"Donald J. Trump","margin":18757,"margin_pct":33.57,"winner":"REP","competitiveness":{"color":"#a50f15"}},"85":{"dem_votes":12899,"rep_votes":36120,"other_votes":578,"total_votes":49597,"dem_candidate":"Joseph R. Biden","rep_candidate":"Donald J. Trump","margin":23221,"margin_pct":46.82,"winner":"REP","competitiveness":{"color":"#67000d"}},"86":{"dem_votes":13118,"rep_votes":31019,"other_votes":465,"total_votes":44602,"dem_candidate":"Joseph R. Biden","rep_candidate":"Donald J. Trump","margin":17901,"margin_pct":40.13,"winner":"REP","competitiveness":{"color":"#67000d"}},"87":{"dem_votes":11556,"rep_votes":33152,"other_votes":514,"total_votes":45222,"dem_candidate":"Joseph R. Biden","rep_candidate":"Donald J. Trump","margin":21596,"margin_pct":47.76,"winner":"REP","competitiveness":{"color":"#67000d"}},"88":{"dem_votes":29668,"rep_votes":12284,"other_votes":835,"total_votes":42787,"dem_candidate":"Joseph R. Biden","rep_candidate":"Donald J. Trump","margin":-17384,"margin_pct":-40.63,"winner":"DEM","competitiveness":{"color":"#08306b"}},"89":{"dem_votes":12413,"rep_votes":36549,"other_votes":622,"total_votes":49584,"dem_candidate":"Joseph R. Biden","rep_candidate":"Donald J. Trump","margin":24136,"margin_pct":48.68,"winner":"REP","competitiveness":{"color":"#67000d"}},"90":{"dem_votes":10076,"rep_votes":33139,"other_votes":451,"total_votes":43666,"dem_candidate":"Joseph R. Biden","rep_candidate":"Donald J. Trump","margin":23063,"margin_pct":52.82,"winner":"REP","competitiveness":{"color":"#67000d"}},"91":{"dem_votes":17418,"rep_votes":36234,"other_votes":664,"total_votes":54316,"dem_candidate":"Joseph R. Biden","rep_candidate":"Donald J. Trump","margin":18816,"margin_pct":34.64,"winner":"REP","competitiveness":{"color":"#a50f15"}},"92":{"dem_votes":29797,"rep_votes":12841,"other_votes":751,"total_votes":43389,"dem_candidate":"Joseph R. Biden","rep_candidate":"Donald J. Trump","margin":-16956,"margin_pct":-39.08,"winner":"DEM","competitiveness":{"color":"#08519c"}},"93":{"dem_votes":21461,"rep_votes":29396,"other_votes":860,"total_votes":51717,"dem_candidate":"Joseph R. Biden","rep_candidate":"Donald J. Trump","margin":7935,"margin_pct":15.34,"winner":"REP","competitiveness":{"color":"#ef3b2c"}},"94":{"dem_votes":10301,"rep_votes":37879,"other_votes":494,"total_votes":48674,"dem_candidate":"Joseph R. Biden","rep_candidate":"Donald J. Trump","margin":27578,"margin_pct":56.66,"winner":"REP","competitiveness":{"color":"#67000d"}},"95":{"dem_votes":12776,"rep_votes":22209,"other_votes":589,"total_votes":35574,"dem_candidate":"Joseph R. Biden","rep_candidate":"Donald J. Trump","margin":9433,"margin_pct":26.52,"winner":"REP","competitiveness":{"color":"#cb181d"}},"96":{"dem_votes":16197,"rep_votes":27891,"other_votes":670,"total_votes":44758,"dem_candidate":"Joseph R. Biden","rep_candidate":"Donald J. Trump","margin":11694,"margin_pct":26.13,"winner":"REP","competitiveness":{"color":"#cb181d"}},"97":{"dem_votes":13274,"rep_votes":36341,"other_votes":602,"total_votes":50217,"dem_candidate":"Joseph R. Biden","rep_candidate":"Donald J. Trump","margin":23067,"margin_pct":45.93,"winner":"REP","competitiveness":{"color":"#67000d"}},"98":{"dem_votes":24483,"rep_votes":22892,"other_votes":750,"total_votes":48125,"dem_candidate":"Joseph R. Biden","rep_candidate":"Donald J. Trump","margin":-1591,"margin_pct":-3.31,"winner":"DEM","competitiveness":{"color":"#c6dbef"}},"99":{"dem_votes":28626,"rep_votes":6253,"other_votes":618,"total_votes":35497,"dem_candidate":"Joseph R. Biden","rep_candidate":"Donald J. Trump","margin":-22373,"margin_pct":-63.03,"winner":"DEM","competitiveness":{"color":"#08306b"}},"100":{"dem_votes":27048,"rep_votes":8742,"other_votes":628,"total_votes":36418,"dem_candidate":"Joseph R. Biden","rep_candidate":"Donald J. Trump","margin":-18306,"margin_pct":-50.27,"winner":"DEM","competitiveness":{"color":"#08306b"}},"101":{"dem_votes":31976,"rep_votes":9941,"other_votes":725,"total_votes":42642,"dem_candidate":"Joseph R. Biden","rep_candidate":"Donald J. Trump","margin":-22035,"margin_pct":-51.67,"winner":"DEM","competitiveness":{"color":"#08306b"}},"102":{"dem_votes":34201,"rep_votes":9589,"other_votes":844,"total_votes":44634,"dem_candidate":"Joseph R. Biden","rep_candidate":"Donald J. Trump","margin":-24612,"margin_pct":-55.14,"winner":"DEM","competitiveness":{"color":"#08306b"}},"103":{"dem_votes":25527,"rep_votes":21990,"other_votes":841,"total_votes":48358,"dem_candidate":"Joseph R. Biden","rep_candidate":"Donald J. Trump","margin":-3537,"margin_pct":-7.31,"winner":"DEM","competitiveness":{"color":"#9ecae1"}},"104":{"dem_votes":26800,"rep_votes":19083,"other_votes":829,"total_votes":46712,"dem_candidate":"Joseph R. Biden","rep_candidate":"Donald J. Trump","margin":-7717,"margin_pct":-16.52,"winner":"DEM","competitiveness":{"color":"#6baed6"}},"105":{"dem_votes":26107,"rep_votes":18269,"other_votes":768,"total_votes":45144,"dem_candidate":"Joseph R. Biden","rep_candidate":"Donald J. Trump","margin":-7838,"margin_pct":-17.36,"winner":"DEM","competitiveness":{"color":"#6baed6"}},"106":{"dem_votes":31284,"rep_votes":13319,"other_votes":706,"total_votes":45309,"dem_candidate":"Joseph R. Biden","rep_candidate":"Donald J. Trump","margin":-17965,"margin_pct":-39.65,"winner":"DEM","competitiveness":{"color":"#08519c"}},"107":{"dem_votes":35334,"rep_votes":8111,"other_votes":722,"total_votes":44167,"dem_candidate":"Joseph R. Biden","rep_candidate":"Donald J. Trump","margin":-27223,"margin_pct":-61.64,"winner":"DEM","competitiveness":{"color":"#08306b"}},"108":{"dem_votes":15195,"rep_votes":30158,"other_votes":618,"total_votes":45971,"dem_candidate":"Joseph R. Biden","rep_candidate":"Donald J. Trump","margin":14963,"margin_pct":32.55,"winner":"REP","competitiveness":{"color":"#a50f15"}},"109":{"dem_votes":13627,"rep_votes":27924,"other_votes":541,"total_votes":42092,"dem_candidate":"Joseph R. Biden","rep_candidate":"Donald J. Trump","margin":14297,"margin_pct":33.97,"winner":"REP","competitiveness":{"color":"#a50f15"}},"110":{"dem_votes":16102,"rep_votes":25340,"other_votes":471,"total_votes":41913,"dem_candidate":"Joseph R. Biden","rep_candidate":"Donald J. Trump","margin":9238,"margin_pct":22.04,"winner":"REP","competitiveness":{"color":"#cb181d"}},"111":{"dem_votes":15295,"rep_votes":33924,"other_votes":569,"total_votes":49788,"dem_candidate":"Joseph R. Biden","rep_candidate":"Donald J. Trump","margin":18629,"margin_pct":37.42,"winner":"REP","competitiveness":{"color":"#a50f15"}},"112":{"dem_votes":27258,"rep_votes":15899,"other_votes":720,"total_votes":43877,"dem_candidate":"Joseph R. Biden","rep_candidate":"Donald J. Trump","margin":-11359,"margin_pct":-25.89,"winner":"DEM","competitiveness":{"color":"#3182bd"}},"113":{"dem_votes":17505,"rep_votes":33306,"other_votes":670,"total_votes":51481,"dem_candidate":"Joseph R. Biden","rep_candidate":"Donald J. Trump","margin":15801,"margin_pct":30.69,"winner":"REP","competitiveness":{"color":"#a50f15"}},"114":{"dem_votes":33587,"rep_votes":20886,"other_votes":923,"total_votes":55396,"dem_candidate":"Joseph R. Biden","rep_candidate":"Donald J. Trump","margin":-12701,"margin_pct":-22.93,"winner":"DEM","competitiveness":{"color":"#3182bd"}},"115":{"dem_votes":31029,"rep_votes":20966,"other_votes":845,"total_votes":52840,"dem_candidate":"Joseph R. Biden","rep_candidate":"Donald J. Trump","margin":-10063,"margin_pct":-19.04,"winner":"DEM","competitiveness":{"color":"#6baed6"}},"116":{"dem_votes":31899,"rep_votes":20560,"other_votes":874,"total_votes":53333,"dem_candidate":"Joseph R. Biden","rep_candidate":"Donald J. Trump","margin":-11339,"margin_pct":-21.26,"winner":"DEM","competitiveness":{"color":"#3182bd"}},"117":{"dem_votes":21733,"rep_votes":31332,"other_votes":910,"total_votes":53975,"dem_candidate":"Joseph R. Biden","rep_candidate":"Donald J. Trump","margin":9599,"margin_pct":17.78,"winner":"REP","competitiveness":{"color":"#ef3b2c"}},"118":{"dem_votes":18045,"rep_votes":30813,"other_votes":760,"total_votes":49618,"dem_candidate":"Joseph R. Biden","rep_candidate":"Donald J. Trump","margin":12768,"margin_pct":25.73,"winner":"REP","competitiveness":{"color":"#cb181d"}},"119":{"dem_votes":20815,"rep_votes":27153,"other_votes":932,"total_votes":48900,"dem_candidate":"Joseph R. Biden","rep_candidate":"Donald J. Trump","margin":6338,"margin_pct":12.96,"winner":"REP","competitiveness":{"color":"#ef3b2c"}},"120":{"dem_votes":12417,"rep_votes":35661,"other_votes":646,"total_votes":48724,"dem_candidate":"Joseph R. Biden","rep_candidate":"Donald J. Trump","margin":23244,"margin_pct":47.71,"winner":"REP","competitiveness":{"color":"#67000d"}}}}}