{"year":2020,"scope":"state_senate","contest_type":"nc_court_of_appeals_judge_seat_05","meta":{"match_coverage_pct":83.5,"matched_precinct_keys":2419,"total_precinct_keys":2897,"source":"batch_shatter_vap_party_split","office":"NC COURT OF APPEALS JUDGE SEAT 05"},"general":{"results":{"1":{"dem_votes":43480,"rep_votes":69816,"other_votes":0,"total_votes":113296,"dem_candidate":"Lora Christine Cubbage","rep_candidate":"Fred Gore","margin":26336,"margin_pct":23.25,"winner":"REP","competitiveness":{"color":"#cb181d"}},"2":{"dem_votes":43321,"rep_votes":60426,"other_votes":0,"total_votes":103747,"dem_candidate":"Lora Christine Cubbage","rep_candidate":"Fred Gore","margin":17105,"margin_pct":16.49,"winner":"REP","competitiveness":{"color":"#ef3b2c"}},"3":{"dem_votes":55432,"rep_votes":49825,"other_votes":0,"total_votes":105257,"dem_candidate":"Lora Christine Cubbage","rep_candidate":"Fred Gore","margin":-5607,"margin_pct":-5.33,"winner":"DEM","competitiveness":{"color":"#c6dbef"}},"4":{"dem_votes":48194,"rep_votes":53852,"other_votes":0,"total_votes":102046,"dem_candidate":"Lora Christine Cubbage","rep_candidate":"Fred Gore","margin":5658,"margin_pct":5.54,"winner":"REP","competitiveness":{"color":"#fb6a4a"}},"5":{"dem_votes":62093,"rep_votes":47452,"other_votes":0,"total_votes":109545,"dem_candidate":"Lora Christine Cubbage","rep_candidate":"Fred Gore","margin":-14641,"margin_pct":-13.37,"winner":"DEM","competitiveness":{"color":"#6baed6"}},"6":{"dem_votes":24156,"rep_votes":44328,"other_votes":0,"total_votes":68484,"dem_candidate":"Lora Christine Cubbage","rep_candidate":"Fred Gore","margin":20172,"margin_pct":29.46,"winner":"REP","competitiveness":{"color":"#cb181d"}},"7":{"dem_votes":56446,"rep_votes":57328,"other_votes":0,"total_votes":113774,"dem_candidate":"Lora Christine Cubbage","rep_candidate":"Fred Gore","margin":882,"margin_pct":0.78,"winner":"REP","competitiveness":{"color":"#fee8c8"}},"8":{"dem_votes":44940,"rep_votes":78351,"other_votes":0,"total_votes":123291,"dem_candidate":"Lora Christine Cubbage","rep_candidate":"Fred Gore","margin":33411,"margin_pct":27.1,"winner":"REP","competitiveness":{"color":"#cb181d"}},"9":{"dem_votes":39524,"rep_votes":62355,"other_votes":0,"total_votes":101879,"dem_candidate":"Lora Christine Cubbage","rep_candidate":"Fred Gore","margin":22831,"margin_pct":22.41,"winner":"REP","competitiveness":{"color":"#cb181d"}},"10":{"dem_votes":39921,"rep_votes":66573,"other_votes":0,"total_votes":106494,"dem_candidate":"Lora Christine Cubbage","rep_candidate":"Fred Gore","margin":26652,"margin_pct":25.03,"winner":"REP","competitiveness":{"color":"#cb181d"}},"11":{"dem_votes":53840,"rep_votes":53963,"other_votes":0,"total_votes":107803,"dem_candidate":"Lora Christine Cubbage","rep_candidate":"Fred Gore","margin":123,"margin_pct":0.11,"winner":"REP","competitiveness":{"color":"#f7f7f7"}},"12":{"dem_votes":34549,"rep_votes":51970,"other_votes":0,"total_votes":86519,"dem_candidate":"Lora Christine Cubbage","rep_candidate":"Fred Gore","margin":17421,"margin_pct":20.14,"winner":"REP","competitiveness":{"color":"#cb181d"}},"13":{"dem_votes":38379,"rep_votes":22990,"other_votes":0,"total_votes":61369,"dem_candidate":"Lora Christine Cubbage","rep_candidate":"Fred Gore","margin":-15389,"margin_pct":-25.08,"winner":"DEM","competitiveness":{"color":"#3182bd"}},"14":{"dem_votes":197668,"rep_votes":129547,"other_votes":0,"total_votes":327215,"dem_candidate":"Lora Christine Cubbage","rep_candidate":"Fred Gore","margin":-68121,"margin_pct":-20.82,"winner":"DEM","competitiveness":{"color":"#3182bd"}},"15":{"dem_votes":38869,"rep_votes":22185,"other_votes":0,"total_votes":61054,"dem_candidate":"Lora Christine Cubbage","rep_candidate":"Fred Gore","margin":-16684,"margin_pct":-27.33,"winner":"DEM","competitiveness":{"color":"#3182bd"}},"16":{"dem_votes":36896,"rep_votes":21134,"other_votes":0,"total_votes":58030,"dem_candidate":"Lora Christine Cubbage","rep_candidate":"Fred Gore","margin":-15762,"margin_pct":-27.16,"winner":"DEM","competitiveness":{"color":"#3182bd"}},"17":{"dem_votes":36289,"rep_votes":23668,"other_votes":0,"total_votes":59957,"dem_candidate":"Lora Christine Cubbage","rep_candidate":"Fred Gore","margin":-12621,"margin_pct":-21.05,"winner":"DEM","competitiveness":{"color":"#3182bd"}},"18":{"dem_votes":40008,"rep_votes":33439,"other_votes":0,"total_votes":73447,"dem_candidate":"Lora Christine Cubbage","rep_candidate":"Fred Gore","margin":-6569,"margin_pct":-8.94,"winner":"DEM","competitiveness":{"color":"#9ecae1"}},"19":{"dem_votes":56702,"rep_votes":45411,"other_votes":0,"total_votes":102113,"dem_candidate":"Lora Christine Cubbage","rep_candidate":"Fred Gore","margin":-11291,"margin_pct":-11.06,"winner":"DEM","competitiveness":{"color":"#6baed6"}},"20":{"dem_votes":118693,"rep_votes":44297,"other_votes":0,"total_votes":162990,"dem_candidate":"Lora Christine Cubbage","rep_candidate":"Fred Gore","margin":-74396,"margin_pct":-45.64,"winner":"DEM","competitiveness":{"color":"#08306b"}},"21":{"dem_votes":46464,"rep_votes":50140,"other_votes":0,"total_votes":96604,"dem_candidate":"Lora Christine Cubbage","rep_candidate":"Fred Gore","margin":3676,"margin_pct":3.81,"winner":"REP","competitiveness":{"color":"#fcae91"}},"22":{"dem_votes":46070,"rep_votes":12956,"other_votes":0,"total_votes":59026,"dem_candidate":"Lora Christine Cubbage","rep_candidate":"Fred Gore","margin":-33114,"margin_pct":-56.1,"winner":"DEM","competitiveness":{"color":"#08306b"}},"23":{"dem_votes":74129,"rep_votes":40419,"other_votes":0,"total_votes":114548,"dem_candidate":"Lora Christine Cubbage","rep_candidate":"Fred Gore","margin":-33710,"margin_pct":-29.43,"winner":"DEM","competitiveness":{"color":"#3182bd"}},"24":{"dem_votes":38584,"rep_votes":40261,"other_votes":0,"total_votes":78845,"dem_candidate":"Lora Christine Cubbage","rep_candidate":"Fred Gore","margin":1677,"margin_pct":2.13,"winner":"REP","competitiveness":{"color":"#fcae91"}},"25":{"dem_votes":43238,"rep_votes":63809,"other_votes":0,"total_votes":107047,"dem_candidate":"Lora Christine Cubbage","rep_candidate":"Fred Gore","margin":20571,"margin_pct":19.22,"winner":"REP","competitiveness":{"color":"#ef3b2c"}},"26":{"dem_votes":52938,"rep_votes":56920,"other_votes":0,"total_votes":109858,"dem_candidate":"Lora Christine Cubbage","rep_candidate":"Fred Gore","margin":3982,"margin_pct":3.62,"winner":"REP","competitiveness":{"color":"#fcae91"}},"27":{"dem_votes":63268,"rep_votes":40577,"other_votes":0,"total_votes":103845,"dem_candidate":"Lora Christine Cubbage","rep_candidate":"Fred Gore","margin":-22691,"margin_pct":-21.85,"winner":"DEM","competitiveness":{"color":"#3182bd"}},"28":{"dem_votes":69078,"rep_votes":39177,"other_votes":0,"total_votes":108255,"dem_candidate":"Lora Christine Cubbage","rep_candidate":"Fred Gore","margin":-29901,"margin_pct":-27.62,"winner":"DEM","competitiveness":{"color":"#3182bd"}},"29":{"dem_votes":35649,"rep_votes":73820,"other_votes":0,"total_votes":109469,"dem_candidate":"Lora Christine Cubbage","rep_candidate":"Fred Gore","margin":38171,"margin_pct":34.87,"winner":"REP","competitiveness":{"color":"#a50f15"}},"30":{"dem_votes":29403,"rep_votes":82523,"other_votes":0,"total_votes":111926,"dem_candidate":"Lora Christine Cubbage","rep_candidate":"Fred Gore","margin":53120,"margin_pct":47.46,"winner":"REP","competitiveness":{"color":"#67000d"}},"31":{"dem_votes":45623,"rep_votes":60158,"other_votes":0,"total_votes":105781,"dem_candidate":"Lora Christine Cubbage","rep_candidate":"Fred Gore","margin":14535,"margin_pct":13.74,"winner":"REP","competitiveness":{"color":"#ef3b2c"}},"32":{"dem_votes":68250,"rep_votes":45579,"other_votes":0,"total_votes":113829,"dem_candidate":"Lora Christine Cubbage","rep_candidate":"Fred Gore","margin":-22671,"margin_pct":-19.92,"winner":"DEM","competitiveness":{"color":"#6baed6"}},"33":{"dem_votes":30986,"rep_votes":72734,"other_votes":0,"total_votes":103720,"dem_candidate":"Lora Christine Cubbage","rep_candidate":"Fred Gore","margin":41748,"margin_pct":40.25,"winner":"REP","competitiveness":{"color":"#67000d"}},"34":{"dem_votes":47520,"rep_votes":59362,"other_votes":0,"total_votes":106882,"dem_candidate":"Lora Christine Cubbage","rep_candidate":"Fred Gore","margin":11842,"margin_pct":11.08,"winner":"REP","competitiveness":{"color":"#ef3b2c"}},"35":{"dem_votes":42711,"rep_votes":71008,"other_votes":0,"total_votes":113719,"dem_candidate":"Lora Christine Cubbage","rep_candidate":"Fred Gore","margin":28297,"margin_pct":24.88,"winner":"REP","competitiveness":{"color":"#cb181d"}},"36":{"dem_votes":24829,"rep_votes":83891,"other_votes":0,"total_votes":108720,"dem_candidate":"Lora Christine Cubbage","rep_candidate":"Fred Gore","margin":59062,"margin_pct":54.32,"winner":"REP","competitiveness":{"color":"#67000d"}},"37":{"dem_votes":39963,"rep_votes":75050,"other_votes":0,"total_votes":115013,"dem_candidate":"Lora Christine Cubbage","rep_candidate":"Fred Gore","margin":35087,"margin_pct":30.51,"winner":"REP","competitiveness":{"color":"#a50f15"}},"38":{"dem_votes":80023,"rep_votes":23260,"other_votes":0,"total_votes":103283,"dem_candidate":"Lora Christine Cubbage","rep_candidate":"Fred Gore","margin":-56763,"margin_pct":-54.96,"winner":"DEM","competitiveness":{"color":"#08306b"}},"39":{"dem_votes":68520,"rep_votes":38654,"other_votes":0,"total_votes":107174,"dem_candidate":"Lora Christine Cubbage","rep_candidate":"Fred Gore","margin":-29866,"margin_pct":-27.87,"winner":"DEM","competitiveness":{"color":"#3182bd"}},"40":{"dem_votes":69362,"rep_votes":29921,"other_votes":0,"total_votes":99283,"dem_candidate":"Lora Christine Cubbage","rep_candidate":"Fred Gore","margin":-39441,"margin_pct":-39.73,"winner":"DEM","competitiveness":{"color":"#08519c"}},"41":{"dem_votes":74757,"rep_votes":36389,"other_votes":0,"total_votes":111146,"dem_candidate":"Lora Christine Cubbage","rep_candidate":"Fred Gore","margin":-38368,"margin_pct":-34.52,"winner":"DEM","competitiveness":{"color":"#08519c"}},"42":{"dem_votes":60263,"rep_votes":51069,"other_votes":0,"total_votes":111332,"dem_candidate":"Lora Christine Cubbage","rep_candidate":"Fred Gore","margin":-9194,"margin_pct":-8.26,"winner":"DEM","competitiveness":{"color":"#9ecae1"}},"43":{"dem_votes":36605,"rep_votes":66340,"other_votes":0,"total_votes":102945,"dem_candidate":"Lora Christine Cubbage","rep_candidate":"Fred Gore","margin":29735,"margin_pct":28.88,"winner":"REP","competitiveness":{"color":"#cb181d"}},"44":{"dem_votes":33486,"rep_votes":72883,"other_votes":0,"total_votes":106369,"dem_candidate":"Lora Christine Cubbage","rep_candidate":"Fred Gore","margin":39397,"margin_pct":37.04,"winner":"REP","competitiveness":{"color":"#a50f15"}},"45":{"dem_votes":32966,"rep_votes":78496,"other_votes":0,"total_votes":111462,"dem_candidate":"Lora Christine Cubbage","rep_candidate":"Fred Gore","margin":45530,"margin_pct":40.85,"winner":"REP","competitiveness":{"color":"#67000d"}},"46":{"dem_votes":38204,"rep_votes":60426,"other_votes":0,"total_votes":98630,"dem_candidate":"Lora Christine Cubbage","rep_candidate":"Fred Gore","margin":22222,"margin_pct":22.53,"winner":"REP","competitiveness":{"color":"#cb181d"}},"47":{"dem_votes":40507,"rep_votes":71181,"other_votes":0,"total_votes":111688,"dem_candidate":"Lora Christine Cubbage","rep_candidate":"Fred Gore","margin":30674,"margin_pct":27.46,"winner":"REP","competitiveness":{"color":"#cb181d"}},"48":{"dem_votes":39651,"rep_votes":72329,"other_votes":0,"total_votes":111980,"dem_candidate":"Lora Christine Cubbage","rep_candidate":"Fred Gore","margin":32678,"margin_pct":29.18,"winner":"REP","competitiveness":{"color":"#cb181d"}},"49":{"dem_votes":74937,"rep_votes":48420,"other_votes":0,"total_votes":123357,"dem_candidate":"Lora Christine Cubbage","rep_candidate":"Fred Gore","margin":-26517,"margin_pct":-21.5,"winner":"DEM","competitiveness":{"color":"#3182bd"}},"50":{"dem_votes":43250,"rep_votes":79287,"other_votes":0,"total_votes":122537,"dem_candidate":"Lora Christine Cubbage","rep_candidate":"Fred Gore","margin":36037,"margin_pct":29.41,"winner":"REP","competitiveness":{"color":"#cb181d"}}}}}